users_fast/__init__.py
users_fast/create.py
users_fast/delete.py
users_fast/read.py
users_fast/update.py
users_fast/users.py
make_operations-1.0.dist-info/METADATA
make_operations-1.0.dist-info/WHEEL
make_operations-1.0.dist-info/top_level.txt
make_operations-1.0.dist-info/RECORD
