Metadata-Version: 2.1
Name: make-operations
Version: 1.0
Summary: Packe developé avec coeur par nafiou
Home-page: UNKNOWN
Author: Waidi Nafiou
Author-email: nafiou94@gmail.com
License: UNKNOWN
Platform: UNKNOWN
Classifier: Programming Language :: Python :: 3
Classifier: License :: OSI Approved :: MIT License
Classifier: Operating System :: OS Independent
